akash_test7/__init__.py
akash_test7-0.0.2.dist-info/DESCRIPTION.rst
akash_test7-0.0.2.dist-info/METADATA
akash_test7-0.0.2.dist-info/RECORD
akash_test7-0.0.2.dist-info/WHEEL
akash_test7-0.0.2.dist-info/metadata.json
akash_test7-0.0.2.dist-info/top_level.txt
