Metadata-Version: 2.0
Name: akash-test7
Version: 0.0.2
Summary: adding number
Home-page: https://github.com/AkashKumarGit/Insurance_Fraud
Author: Akash Kumar
Author-email: kumarakash631@gmail.com
License: UNKNOWN
Platform: UNKNOWN
Classifier: Programming Language :: Python :: 3
Classifier: License :: OSI Approved :: MIT License
Classifier: Operating System :: OS Independent
